kodipydent/KodiClient.py
kodipydent/__init__.py
kodipydent/hive.json
kodipydent/rpctohive.py
kodipydent_alt-2022.9.3.dist-info/LICENSE
kodipydent_alt-2022.9.3.dist-info/WHEEL
kodipydent_alt-2022.9.3.dist-info/METADATA
kodipydent_alt-2022.9.3.dist-info/RECORD
