Metadata-Version: 2.1
Name: kodipydent-alt
Version: 2022.9.3
Summary: A complete Python client for the Kodi JSON-RPC API
Home-page: https://github.com/miigotu/kodipydent
License: MIT
Keywords: Kodi,JSON-RPC,JSONRPC,RPC,JSON,client,XBMC
Author: Jesse Shapiro
Author-email: jesse@bedrockdata.com
Maintainer: Dustyn Gibson
Maintainer-email: miigotu@gmail.com
Requires-Python: >=3.7.2,<4
Classifier: Development Status :: 4 - Beta
Classifier: Intended Audience :: Developers
Classifier: Intended Audience :: Information Technology
Classifier: Intended Audience :: System Administrators
Classifier: License :: OSI Approved :: MIT License
Classifier: Operating System :: OS Independent
Classifier: Programming Language :: Python
Classifier: Programming Language :: Python :: 3
Classifier: Programming Language :: Python :: 3.8
Classifier: Programming Language :: Python :: 3.9
Classifier: Programming Language :: Python :: 3.10
Classifier: Programming Language :: Python :: 3
Classifier: Programming Language :: Python :: 3 :: Only
Classifier: Programming Language :: Python :: 3.10
Classifier: Programming Language :: Python :: 3.11
Classifier: Programming Language :: Python :: 3.12
Classifier: Programming Language :: Python :: 3.7
Classifier: Programming Language :: Python :: 3.8
Classifier: Programming Language :: Python :: 3.9
Classifier: Topic :: Internet
Classifier: Topic :: Internet :: WWW/HTTP
Classifier: Topic :: Software Development :: Libraries
Classifier: Topic :: Software Development :: Libraries :: Python Modules
Classifier: Topic :: Utilities
Requires-Dist: beekeeper-alt (>=2022.9.3,<2023.0.0)
Project-URL: Repository, https://github.com/miigotu/kodipydent
